INSTALL.rst
MANIFEST.in
README.rst
setup.cfg
setup.py
docs/HISTORY.txt
docs/INSTALL.txt
docs/LICENSE.GPL
docs/LICENSE.txt
gloss/__init__.py
gloss.theme.egg-info/PKG-INFO
gloss.theme.egg-info/SOURCES.txt
gloss.theme.egg-info/dependency_links.txt
gloss.theme.egg-info/entry_points.txt
gloss.theme.egg-info/namespace_packages.txt
gloss.theme.egg-info/not-zip-safe
gloss.theme.egg-info/requires.txt
gloss.theme.egg-info/top_level.txt
gloss/theme/__init__.py
gloss/theme/configure.zcml
gloss/theme/interfaces.py
gloss/theme/version.txt
gloss/theme/diazo_resources/README.txt
gloss/theme/diazo_resources/custom-css.xml
gloss/theme/diazo_resources/custom.xml
gloss/theme/diazo_resources/favicon.ico
gloss/theme/diazo_resources/gloss.xml
gloss/theme/diazo_resources/grid-webflow.xml
gloss/theme/diazo_resources/index.html
gloss/theme/diazo_resources/manifest.cfg
gloss/theme/diazo_resources/preview.png
gloss/theme/diazo_resources/rules.xml
gloss/theme/diazo_resources/css/glossinator.webflow.css
gloss/theme/diazo_resources/css/normalize.css
gloss/theme/diazo_resources/css/webflow.css
gloss/theme/diazo_resources/images/1416642820_clipboard.png
gloss/theme/diazo_resources/images/email-icon.png
gloss/theme/diazo_resources/images/favicon.ico
gloss/theme/diazo_resources/images/favicon.png
gloss/theme/diazo_resources/images/flowersky.jpg
gloss/theme/diazo_resources/images/twitter-icon.png
gloss/theme/diazo_resources/js/modernizr.js
gloss/theme/diazo_resources/js/webflow.js
gloss/theme/diazo_resources/less/accessibility.plone.less
gloss/theme/diazo_resources/less/alerts.plone.less
gloss/theme/diazo_resources/less/barceloneta-compiled.css
gloss/theme/diazo_resources/less/barceloneta-compiled.css.map
gloss/theme/diazo_resources/less/barceloneta.css
gloss/theme/diazo_resources/less/barceloneta.plone.export.less
gloss/theme/diazo_resources/less/barceloneta.plone.less
gloss/theme/diazo_resources/less/barceloneta.plone.local.less
gloss/theme/diazo_resources/less/behaviors.plone.less
gloss/theme/diazo_resources/less/breadcrumbs.plone.less
gloss/theme/diazo_resources/less/buttons.plone.less
gloss/theme/diazo_resources/less/code.plone.less
gloss/theme/diazo_resources/less/contents.plone.less
gloss/theme/diazo_resources/less/controlpanels.plone.less
