Metadata-Version: 1.1
Name: gloss.theme
Version: 0.8.4
Summary: gloss.theme
Home-page: https://github.com/glossproject/gloss.theme
Author: David Bain
Author-email: david@alteroo.com
License: GPL
Keywords: theme,gloss
Platform: UNKNOWN
Classifier: Framework :: Plone
Classifier: Programming Language :: Python
Classifier: Topic :: Software Development :: Libraries :: Python Modules
